kwark/__init__.py
kwark/__main__.py
kwark/ai_services/__init__.py
kwark/ai_services/anthropic_ai_service.py
kwark/ai_services/mcp_client.py
kwark/command/__init__.py
kwark/command/activate_command.py
kwark/command/branch_command.py
kwark/command/chat_command.py
kwark/command/commit_command.py
kwark/command/doc_command.py
kwark/command/models_command.py
kwark/prompts/branch.txt
kwark/prompts/commit.txt
kwark/prompts/doc.txt
kwark/util.py
kwark-1.10.0.dist-info/METADATA
kwark-1.10.0.dist-info/WHEEL
kwark-1.10.0.dist-info/entry_points.txt
kwark-1.10.0.dist-info/RECORD
