Metadata-Version: 2.4
Name: kwark
Version: 1.10.0
Summary: Tap into AI brilliance from a simple shell command
License: MIT
Author: SteamWiz Labs
Author-email: kwark@steamwiz.io
Requires-Python: >=3.13,<4.0
Classifier: License :: OSI Approved :: MIT License
Classifier: Programming Language :: Python :: 3
Classifier: Programming Language :: Python :: 3.13
Classifier: Programming Language :: Python :: 3.14
Requires-Dist: anthropic (>=0.75.0,<0.76.0)
Requires-Dist: mcp (>=1.25.0,<2.0.0)
Requires-Dist: requests (>=2.32.5,<3.0.0)
Requires-Dist: wizlib (>=3.4.0,<4.0.0)
